{
  "wspolczynniki_poprawkowe_beta": [
    {"typ_przegrody": "ściana", "masa_od": 200, "masa_do": 300, "beta_P_3": 1.5, "beta_P_5": -1.5},
    {"typ_przegrody": "ściana", "masa_od": 500, "masa_do": 700, "beta_P_3": 1.0, "beta_P_5": -1.0},
    {"typ_przegrody": "stropodach", "masa_od": 50, "masa_do": 200, "beta_P_3": 2.0, "beta_P_5": -2.0},
    {"typ_przegrody": "stropodach", "masa_od": 300, "masa_do": 500, "beta_P_3": 1.5, "beta_P_5": -1.5}
  ],
  "rownowazna_roznica_temperatury_dt_r": [
    {"przegroda": "ściana", "wariant": "NE", "masa_kg_m2": 100, "godziny": {"6": -7.0, "7": -5.4, "8": -1.5, "9": 1.7, "10": 3.4, "11": 4.6, "12": 5.2, "13": 5.6, "14": 5.9, "15": 6.0, "16": 5.9, "17": 5.7, "18": 5.5, "19": 5.1, "20": 4.7}},
    {"przegroda": "ściana", "wariant": "NE", "masa_kg_m2": 200, "godziny": {"6": -3.7, "7": -3.1, "8": -2.5, "9": -1.7, "10": -0.9, "11": 0.0, "12": 0.9, "13": 1.9, "14": 2.8, "15": 3.6, "16": 4.1, "17": 4.4, "18": 4.3, "19": 4.0, "20": 3.6}},
    {"przegroda": "ściana", "wariant": "NE", "masa_kg_m2": 300, "godziny": {"6": -0.5, "7": -0.9, "8": -1.1, "9": -1.2, "10": -1.2, "11": -1.1, "12": -1.0, "13": -0.7, "14": -0.5, "15": -0.1, "16": 0.3, "17": 0.7, "18": 1.3, "19": 1.9, "20": 2.5}},
    
    {"przegroda": "ściana", "wariant": "E", "masa_kg_m2": 100, "godziny": {"6": -7.2, "7": -6.0, "8": -0.9, "9": 6.0, "10": 9.6, "11": 11.8, "12": 12.4, "13": 11.7, "14": 10.6, "15": 9.5, "16": 8.8, "17": 8.0, "18": 7.3, "19": 6.7, "20": 6.2}},
    {"przegroda": "ściana", "wariant": "E", "masa_kg_m2": 200, "godziny": {"6": -2.0, "7": -1.7, "8": -0.9, "9": 0.8, "10": 2.9, "11": 6.0, "12": 7.2, "13": 7.6, "14": 7.7, "15": 7.5, "16": 7.2, "17": 6.8, "18": 6.5, "19": 6.2, "20": 6.0}},
    {"przegroda": "ściana", "wariant": "E", "masa_kg_m2": 300, "godziny": {"6": 1.3, "7": 0.7, "8": 0.3, "9": 0.2, "10": 0.4, "11": 0.8, "12": 1.5, "13": 2.2, "14": 2.9, "15": 3.5, "16": 4.0, "17": 4.5, "18": 4.8, "19": 5.0, "20": 5.1}},
    
    {"przegroda": "ściana", "wariant": "SE", "masa_kg_m2": 100, "godziny": {"6": -7.8, "7": -7.9, "8": -6.0, "9": 1.1, "10": 5.8, "11": 9.8, "12": 13.3, "13": 14.8, "14": 15.1, "15": 14.6, "16": 13.3, "17": 11.7, "18": 10.0, "19": 8.8, "20": 7.6}},
    {"przegroda": "ściana", "wariant": "SE", "masa_kg_m2": 200, "godziny": {"6": -2.7, "7": -2.3, "8": -1.7, "9": -0.7, "10": 0.9, "11": 3.8, "12": 7.7, "13": 9.4, "14": 10.0, "15": 10.0, "16": 9.7, "17": 8.9, "18": 8.0, "19": 7.5, "20": 7.2}},
    {"przegroda": "ściana", "wariant": "SE", "masa_kg_m2": 300, "godziny": {"6": 1.4, "7": 0.7, "8": 0.3, "9": 0.7, "10": 0.1, "11": 0.4, "12": 0.8, "13": 1.5, "14": 2.2, "15": 3.2, "16": 4.4, "17": 5.2, "18": 5.7, "19": 5.9, "20": 6.0}},
    
    {"przegroda": "ściana", "wariant": "S", "masa_kg_m2": 100, "godziny": {"6": -7.5, "7": -8.3, "8": -8.5, "9": -8.1, "10": -5.4, "11": 1.8, "12": 6.7, "13": 11.4, "14": 14.8, "15": 16.7, "16": 16.8, "17": 16.0, "18": 14.4, "19": 12.5, "20": 10.7}},
    {"przegroda": "ściana", "wariant": "S", "masa_kg_m2": 200, "godziny": {"6": -2.6, "7": -3.5, "8": -4.0, "9": -4.0, "10": -3.4, "11": -2.0, "12": 0.0, "13": 3.0, "14": 7.8, "15": 10.2, "16": 11.1, "17": 11.1, "18": 10.5, "19": 9.2, "20": 8.0}},
    {"przegroda": "ściana", "wariant": "S", "masa_kg_m2": 300, "godziny": {"6": 1.4, "7": 0.9, "8": 0.4, "9": -0.3, "10": -1.0, "11": -1.3, "12": -1.2, "13": -0.8, "14": -0.2, "15": 0.7, "16": 1.8, "17": 3.3, "18": 4.5, "19": 5.4, "20": 5.9}},
    
    {"przegroda": "ściana", "wariant": "SW", "masa_kg_m2": 100, "godziny": {"6": -7.0, "7": -8.0, "8": -8.4, "9": -8.2, "10": -7.3, "11": -5.1, "12": -1.5, "13": 3.5, "14": 8.6, "15": 16.4, "16": 19.7, "17": 20.9, "18": 20.8, "19": 20.0, "20": 18.0}},
    {"przegroda": "ściana", "wariant": "SW", "masa_kg_m2": 200, "godziny": {"6": -0.9, "7": -2.1, "8": -2.9, "9": -3.3, "10": -3.2, "11": -2.8, "12": -2.0, "13": -0.5, "14": 2.7, "15": 7.9, "16": 11.5, "17": 13.5, "18": 14.2, "19": 13.9, "20": 12.6}},
    {"przegroda": "ściana", "wariant": "SW", "masa_kg_m2": 300, "godziny": {"6": 2.7, "7": 1.9, "8": 1.3, "9": 0.7, "10": 0.3, "11": 0.0, "12": -0.2, "13": -0.2, "14": 0.1, "15": 0.5, "16": 1.1, "17": 2.0, "18": 3.3, "19": 4.9, "20": 6.8}},
    
    {"przegroda": "ściana", "wariant": "W", "masa_kg_m2": 100, "godziny": {"6": -6.1, "7": -7.5, "8": -7.9, "9": -7.8, "10": -7.1, "11": -5.5, "12": -2.6, "13": 0.9, "14": 4.0, "15": 8.2, "16": 11.5, "17": 14.8, "18": 17.4, "19": 19.8, "20": 21.7}},
    {"przegroda": "ściana", "wariant": "W", "masa_kg_m2": 200, "godziny": {"6": -0.3, "7": -2.1, "8": -2.8, "9": -3.1, "10": -3.1, "11": -2.8, "12": -2.2, "13": -1.2, "14": 0.4, "15": 3.0, "16": 7.1, "17": 9.6, "18": 11.7, "19": 13.2, "20": 14.4}},
    {"przegroda": "ściana", "wariant": "W", "masa_kg_m2": 300, "godziny": {"6": 2.9, "7": 2.0, "8": 1.4, "9": 0.7, "10": 0.2, "11": -0.2, "12": -0.5, "13": -0.5, "14": -0.4, "15": 0.0, "16": 0.4, "17": 1.2, "18": 2.3, "19": 3.6, "20": 5.4}},
    
    {"przegroda": "ściana", "wariant": "NW", "masa_kg_m2": 100, "godziny": {"6": -6.8, "7": -7.6, "8": -7.9, "9": -7.7, "10": -6.8, "11": -5.0, "12": -2.9, "13": -0.5, "14": 1.7, "15": 4.4, "16": 7.1, "17": 10.7, "18": 14.0, "19": 14.8, "20": 13.6}},
    {"przegroda": "ściana", "wariant": "NW", "masa_kg_m2": 200, "godziny": {"6": -2.0, "7": -3.0, "8": -3.7, "9": -4.1, "10": -4.3, "11": -4.0, "12": -3.2, "13": -2.0, "14": -0.7, "15": 0.9, "16": 2.9, "17": 6.0, "18": 8.3, "19": 9.4, "20": 9.7}},
    {"przegroda": "ściana", "wariant": "NW", "masa_kg_m2": 300, "godziny": {"6": 0.7, "7": 0.2, "8": -0.3, "9": -0.8, "10": -1.2, "11": -1.5, "12": -1.8, "13": -1.9, "14": -1.8, "15": -1.5, "16": -1.0, "17": -0.3, "18": 0.3, "19": 1.1, "20": 1.9}},
    
    {"przegroda": "ściana", "wariant": "N", "masa_kg_m2": 100, "godziny": {"6": -7.6, "7": -7.8, "8": -7.6, "9": -7.0, "10": -5.9, "11": -4.2, "12": -2.4, "13": 0.4, "14": 2.5, "15": 3.9, "16": 4.7, "17": 5.1, "18": 5.3, "19": 5.3, "20": 5.0}},
    {"przegroda": "ściana", "wariant": "N", "masa_kg_m2": 200, "godziny": {"6": -4.0, "7": -4.5, "8": -4.7, "9": -4.7, "10": -4.6, "11": -4.3, "12": -3.5, "13": -2.2, "14": -0.4, "15": 1.0, "16": 1.9, "17": 2.6, "18": 3.0, "19": 3.2, "20": 3.3}},
    {"przegroda": "ściana", "wariant": "N", "masa_kg_m2": 300, "godziny": {"6": -1.7, "7": -2.2, "8": -2.7, "9": -3.0, "10": -3.1, "11": -3.2, "12": -3.1, "13": -3.0, "14": -2.8, "15": -2.6, "16": -2.2, "17": -1.8, "18": -1.3, "19": -0.8, "20": -0.3}},
    
    {"przegroda": "stropodach", "wariant": "ocieplony_nasłoneczniony", "masa_kg_m2": 50, "godziny": {"6": -8.8, "7": -3.0, "8": 4.4, "9": 13.7, "10": 23.7, "11": 32.0, "12": 40.8, "13": 42.8, "14": 42.7, "15": 41.2, "16": 37.2, "17": 33.3, "18": 28.0, "19": 21.2, "20": 14.2}},
    {"przegroda": "stropodach", "wariant": "ocieplony_nasłoneczniony", "masa_kg_m2": 100, "godziny": {"6": -1.4, "7": -3.0, "8": -3.3, "9": -2.2, "10": 2.0, "11": 9.2, "12": 16.0, "13": 23.0, "14": 30.0, "15": 33.0, "16": 33.6, "17": 32.7, "18": 30.2, "19": 26.7, "20": 23.0}},
    {"przegroda": "stropodach", "wariant": "ocieplony_nasłoneczniony", "masa_kg_m2": 500, "godziny": {"6": -3.6, "7": -4.1, "8": -4.5, "9": -4.8, "10": -5.0, "11": -5.2, "12": -5.2, "13": -5.1, "14": -5.0, "15": -4.7, "16": -4.5, "17": -4.1, "18": -3.6, "19": -3.1, "20": -2.5}},
    
    {"przegroda": "stropodach", "wariant": "nieocieplony_nasłoneczniony", "masa_kg_m2": 50, "godziny": {"6": -6.3, "7": -5.8, "8": -4.9, "9": -2.6, "10": 1.0, "11": 7.0, "12": 13.0, "13": 17.8, "14": 22.0, "15": 25.3, "16": 27.1, "17": 27.3, "18": 26.0, "19": 23.6, "20": 19.8}},
    {"przegroda": "stropodach", "wariant": "nieocieplony_nasłoneczniony", "masa_kg_m2": 100, "godziny": {"6": 0.4, "7": -0.5, "8": -0.6, "9": -0.2, "10": 0.9, "11": 3.4, "12": 7.6, "13": 12.6, "14": 18.0, "15": 22.4, "16": 26.4, "17": 28.8, "18": 29.2, "19": 28.2, "20": 25.3}},
    {"przegroda": "stropodach", "wariant": "nieocieplony_nasłoneczniony", "masa_kg_m2": 200, "godziny": {"6": 7.3, "7": 5.2, "8": 4.0, "9": 3.4, "10": 4.0, "11": 5.9, "12": 7.8, "13": 10.0, "14": 11.8, "15": 13.5, "16": 15.0, "17": 16.3, "18": 17.5, "19": 18.6, "20": 19.5}},
    {"przegroda": "stropodach", "wariant": "nieocieplony_nasłoneczniony", "masa_kg_m2": 300, "godziny": {"6": 5.8, "7": 5.4, "8": 5.1, "9": 5.2, "10": 5.6, "11": 6.4, "12": 7.4, "13": 8.7, "14": 10.2, "15": 11.9, "16": 13.6, "17": 15.1, "18": 16.2, "19": 16.9, "20": 17.2}},
    {"przegroda": "stropodach", "wariant": "nieocieplony_nasłoneczniony", "masa_kg_m2": 500, "godziny": {"6": 8.6, "7": 7.9, "8": 7.5, "9": 7.3, "10": 7.2, "11": 7.3, "12": 7.5, "13": 7.9, "14": 8.4, "15": 9.1, "16": 10.0, "17": 11.0, "18": 12.3, "19": 13.7, "20": 14.8}},
    
    {"przegroda": "stropodach", "wariant": "nieocieplony_zacieniony", "masa_kg_m2": 50, "godziny": {"6": -9.1, "7": -9.4, "8": -9.2, "9": -8.7, "10": -7.8, "11": -6.5, "12": -5.1, "13": -3.4, "14": -2.0, "15": -0.7, "16": 0.4, "17": 1.1, "18": 1.6, "19": 1.7, "20": 1.4}},
    {"przegroda": "stropodach", "wariant": "nieocieplony_zacieniony", "masa_kg_m2": 100, "godziny": {"6": -6.2, "7": -6.9, "8": -7.2, "9": -7.2, "10": -7.0, "11": -6.5, "12": -5.8, "13": -4.6, "14": -3.2, "15": -1.7, "16": -0.5, "17": 0.6, "18": 1.5, "19": 2.1, "20": 2.4}},
    {"przegroda": "stropodach", "wariant": "nieocieplony_zacieniony", "masa_kg_m2": 200, "godziny": {"6": -3.6, "7": -4.4, "8": -4.9, "9": -5.4, "10": -5.7, "11": -5.7, "12": -5.3, "13": -4.6, "14": -4.0, "15": -3.4, "16": -2.9, "17": -2.4, "18": -2.1, "19": -1.7, "20": -1.4}},
    {"przegroda": "stropodach", "wariant": "nieocieplony_zacieniony", "masa_kg_m2": 300, "godziny": {"6": -4.8, "7": -5.0, "8": -5.2, "9": -5.3, "10": -5.3, "11": -5.2, "12": -5.0, "13": -4.7, "14": -4.3, "15": -3.8, "16": -3.4, "17": -2.9, "18": -2.5, "19": -2.1, "20": -1.7}},
    {"przegroda": "stropodach", "wariant": "nieocieplony_zacieniony", "masa_kg_m2": 500, "godziny": {"6": -3.7, "7": -4.0, "8": -4.1, "9": -4.3, "10": -4.5, "11": -4.5, "12": -4.5, "13": -4.5, "14": -4.5, "15": -4.4, "16": -4.2, "17": -4.0, "18": -3.7, "19": -3.2, "20": -2.8}}
  ]
}